backslant.py
backslant/__init__.py
backslant/flask.py
backslant/lexer.py
backslant/parser.py
backslant-0.3.8.dist-info/DESCRIPTION.rst
backslant-0.3.8.dist-info/METADATA
backslant-0.3.8.dist-info/RECORD
backslant-0.3.8.dist-info/WHEEL
backslant-0.3.8.dist-info/metadata.json
backslant-0.3.8.dist-info/top_level.txt
