Metadata-Version: 2.0
Name: backslant
Version: 0.3.8
Summary: Python template engine.
Home-page: https://github.com/Deepwalker/backslant/
Author: Deepwalker
Author-email: krivushinme@gmail.com
License: BSD
Keywords: template html ast jinja2 mako slim plim
Platform: UNKNOWN
Classifier: Intended Audience :: Developers
Classifier: License :: OSI Approved :: BSD License
Classifier: Operating System :: OS Independent
Classifier: Programming Language :: Python
Classifier: Programming Language :: Python :: 3
Requires-Dist: funcparserlib
Requires-Dist: markupsafe
